missingforest/__init__.py
missingforest/knnimpute.py
missingforest/missforest.py
missingforest/pairwise_external.py
missingforest/utils.py
missingforest/tests/__init__.py
missingforest/tests/test_knnimpute.py
missingforest/tests/test_missforest.py
missingforest-0.4.1.dist-info/LICENSE
missingforest-0.4.1.dist-info/METADATA
missingforest-0.4.1.dist-info/WHEEL
missingforest-0.4.1.dist-info/top_level.txt
missingforest-0.4.1.dist-info/RECORD
