Metadata-Version: 2.1
Name: missingforest
Version: 0.4.1
Summary: Missing Data Imputation for Python : Package was forked from missingpy 0.2.0
Home-page: https://github.com/rictjo/missingpy
Author: Richard Tjörnhammar
Author-email: richard.tjornhammar@gmail.com
Classifier: Programming Language :: Python :: 3.9
Classifier: License :: OSI Approved :: GNU General Public License v3 (GPLv3)
Classifier: Operating System :: OS Independent
License-File: LICENSE
